LICENSE
mreschke/serverbackups/__init__.py
mreschke/serverbackups/backups.py
mreschke/serverbackups/backupserver.py
mreschke/serverbackups/cli.py
mreschke/serverbackups/examples/api_dict_local_to_local.py
mreschke/serverbackups/examples/api_dict_local_to_remote.py
mreschke/serverbackups/examples/cli_dict_local_to_local.py
mreschke/serverbackups/examples/cli_dict_local_to_remote.py
mreschke/serverbackups/examples/example_server_configd.yml
mreschke/serverbackups/init.py
mreschke/serverbackups/log.py
mreschke/serverbackups/templates/backups_api.py
mreschke/serverbackups/templates/backups_cli.py
mreschke/serverbackups/templates/defaults.yml
mreschke/serverbackups/templates/defaults_blank.yml
mreschke/serverbackups/templates/server_configd.yml
mreschke/serverbackups/utils.py
mreschke_serverbackups-1.0.8.dist-info/LICENSE
mreschke_serverbackups-1.0.8.dist-info/METADATA
mreschke_serverbackups-1.0.8.dist-info/WHEEL
mreschke_serverbackups-1.0.8.dist-info/entry_points.txt
mreschke_serverbackups-1.0.8.dist-info/RECORD
