Metadata-Version: 2.1
Name: mreschke-serverbackups
Version: 1.0.8
Summary: Config driven server backups that feel like a simple backup.py script
Home-page: http://github.com/mreschke/server-backups
License: MIT
Author: Matthew Reschke
Author-email: mail@mreschke.com
Requires-Python: >=3.5,<4.0
Classifier: Environment :: Console
Classifier: Intended Audience :: Information Technology
Classifier: Intended Audience :: System Administrators
Classifier: License :: OSI Approved :: MIT License
Classifier: Operating System :: MacOS
Classifier: Operating System :: POSIX
Classifier: Operating System :: Unix
Classifier: Programming Language :: Python :: 3
Classifier: Programming Language :: Python :: 3.5
Classifier: Programming Language :: Python :: 3.6
Classifier: Programming Language :: Python :: 3.7
Classifier: Programming Language :: Python :: 3.8
Classifier: Programming Language :: Python :: 3.9
Classifier: Programming Language :: Python :: 3.10
Classifier: Programming Language :: Python :: 3.11
Classifier: Topic :: System :: Archiving :: Backup
Requires-Dist: PyYAML (==5.3.1)
Requires-Dist: click (==7.1.2)
Requires-Dist: colored (==1.4.2)
Requires-Dist: prettyprinter (==0.18.0)
Project-URL: Documentation, http://github.com/mreschke/server-backups
Project-URL: Repository, http://github.com/mreschke/server-backups
